datatoolsdemo/__init__.py
datatoolsdemo/clean.py
datatoolsdemo/fetch.py
datatoolsdemo/plot.py
datatoolsdemo/shipping.py
datatoolsdemo-0.0.8.dist-info/METADATA
datatoolsdemo-0.0.8.dist-info/WHEEL
datatoolsdemo-0.0.8.dist-info/licenses/LICENCE
datatoolsdemo-0.0.8.dist-info/RECORD
